{
    "response": {
        "explain": " The previous action code has successfully executed the subtask of grasping the book (hardback_188). The robot now has the book in its inventory. The next step is to move the robot to the carton (carton_195).",
        "subtask": "\n(1) Move the robot to the book (hardback_188).\n(2) Grasp the book (hardback_188).\n(3) Move the robot to the carton (carton_195).\n(4) Open the carton (carton_195).\n(5) Put the book (hardback_188) inside the carton (carton_195).",
        "code": "def act(robot,env,camera):\n    # Subtask 3: Move the robot to the carton (carton_195)\n    carton_195 = registry(env,\"carton_195\")\n    MoveBot(env, robot, carton_195, camera)\n    donothing(env)\n",
        "inventory": "hardback_188",
        "obj_2": [],
        "obj_3": [
            [
                "robot",
                "nextto",
                "carton_195",
                "1"
            ]
        ]
    }
}