{
    "task": "put_carboy_in_the_bin",
    "0_detect_surroundings": {
        "recycling_bin_188": {
            "ability": [
                [
                    "openable",
                    0
                ],
                [
                    "heatable",
                    0
                ],
                [
                    "freezable",
                    0
                ]
            ],
            "position_in_bot": {
                "rho": 2.41759060995763,
                "theta_deg": 90.06364566127347,
                "phi_deg": 84.32263375970346
            },
            "orientation_in_bot": [
                0.004613401342793831,
                0.023148828927239552,
                0.17622606664497878,
                0.984066675425089
            ],
            "position_in_world": [
                -4.088426113128662,
                -3.421128511428833,
                0.2439800351858139
            ],
            "bot_in_world": [
                -5.75587797164917,
                -5.155238628387451,
                0.0047920942306518555
            ],
            "path": "./prompt_files/data/put_carboy_in_the_bin/subtask_2/seg_instance0_detect_surroundings.png"
        },
        "reagent_bottle_189": {
            "ability": [
                [
                    "heatable",
                    0
                ],
                [
                    "freezable",
                    0
                ]
            ],
            "position_in_bot": {
                "rho": 1.2777986519831164,
                "theta_deg": 124.3336612892029,
                "phi_deg": 78.87468596121239
            },
            "orientation_in_bot": [
                0.0017944523899950276,
                0.021940433299487343,
                0.08607571568419964,
                0.9960453646780871
            ],
            "position_in_world": [
                -5.548537731170654,
                -3.912888765335083,
                0.22007398307323456
            ],
            "bot_in_world": [
                -5.75587797164917,
                -5.155238628387451,
                0.0047920942306518555
            ],
            "path": "./prompt_files/data/put_carboy_in_the_bin/subtask_2/seg_instance0_detect_surroundings.png"
        },
        "bottom_cabinet_no_top_qudfwe_0": {
            "ability": [
                [
                    "openable",
                    0
                ],
                [
                    "heatable",
                    0
                ],
                [
                    "freezable",
                    0
                ]
            ],
            "position_in_bot": {
                "rho": 1.296098025909153,
                "theta_deg": 133.5265002053048,
                "phi_deg": 69.33677181039076
            },
            "orientation_in_bot": [
                0.008227525681410065,
                0.020472777400229545,
                0.3760714845158647,
                0.9263279180402134
            ],
            "position_in_world": [
                -5.7557172775268555,
                -3.9291481971740723,
                0.4249972403049469
            ],
            "bot_in_world": [
                -5.75587797164917,
                -5.155238628387451,
                0.0047920942306518555
            ],
            "path": "./prompt_files/data/put_carboy_in_the_bin/subtask_2/seg_instance0_detect_surroundings.png"
        },
        "scene_graph": [
            [
                "reagent_bottle_189",
                "inside",
                "bottom_cabinet_no_top_qudfwe_0"
            ]
        ],
        "inventory": []
    },
    "1_detect_surroundings": {
        "recycling_bin_188": {
            "ability": [
                [
                    "openable",
                    0
                ],
                [
                    "heatable",
                    0
                ],
                [
                    "freezable",
                    0
                ]
            ],
            "position_in_bot": {
                "rho": 2.41759060995763,
                "theta_deg": 90.06364566127347,
                "phi_deg": 84.32263375970346
            },
            "orientation_in_bot": [
                0.004613401342793831,
                0.023148828927239552,
                0.17622606664497878,
                0.984066675425089
            ],
            "position_in_world": [
                -4.088426113128662,
                -3.421128511428833,
                0.2439800351858139
            ],
            "bot_in_world": [
                -5.75587797164917,
                -5.155238628387451,
                0.0047920942306518555
            ],
            "path": "./prompt_files/data/put_carboy_in_the_bin/subtask_2/seg_instance1_detect_surroundings.png"
        },
        "reagent_bottle_189": {
            "ability": [
                [
                    "heatable",
                    0
                ],
                [
                    "freezable",
                    0
                ]
            ],
            "position_in_bot": {
                "rho": 1.2777986519831164,
                "theta_deg": 124.3336612892029,
                "phi_deg": 78.87468596121239
            },
            "orientation_in_bot": [
                0.0017944523899950276,
                0.021940433299487343,
                0.08607571568419964,
                0.9960453646780871
            ],
            "position_in_world": [
                -5.548537731170654,
                -3.912888765335083,
                0.22007398307323456
            ],
            "bot_in_world": [
                -5.75587797164917,
                -5.155238628387451,
                0.0047920942306518555
            ],
            "path": "./prompt_files/data/put_carboy_in_the_bin/subtask_2/seg_instance1_detect_surroundings.png"
        },
        "bottom_cabinet_no_top_qudfwe_0": {
            "ability": [
                [
                    "openable",
                    0
                ],
                [
                    "heatable",
                    0
                ],
                [
                    "freezable",
                    0
                ]
            ],
            "position_in_bot": {
                "rho": 1.296098025909153,
                "theta_deg": 133.5265002053048,
                "phi_deg": 69.33677181039076
            },
            "orientation_in_bot": [
                0.008227525681410065,
                0.020472777400229545,
                0.3760714845158647,
                0.9263279180402134
            ],
            "position_in_world": [
                -5.7557172775268555,
                -3.9291481971740723,
                0.4249972403049469
            ],
            "bot_in_world": [
                -5.75587797164917,
                -5.155238628387451,
                0.0047920942306518555
            ],
            "path": "./prompt_files/data/put_carboy_in_the_bin/subtask_2/seg_instance1_detect_surroundings.png"
        },
        "scene_graph": [
            [
                "reagent_bottle_189",
                "inside",
                "bottom_cabinet_no_top_qudfwe_0"
            ]
        ],
        "inventory": []
    },
    "2_detect_surroundings": {
        "recycling_bin_188": {
            "ability": [
                [
                    "openable",
                    0
                ],
                [
                    "heatable",
                    0
                ],
                [
                    "freezable",
                    0
                ]
            ],
            "position_in_bot": {
                "rho": 2.41759060995763,
                "theta_deg": 90.06364566127347,
                "phi_deg": 84.32263375970346
            },
            "orientation_in_bot": [
                0.004613401342793831,
                0.023148828927239552,
                0.17622606664497878,
                0.984066675425089
            ],
            "position_in_world": [
                -4.088426113128662,
                -3.421128511428833,
                0.2439800351858139
            ],
            "bot_in_world": [
                -5.75587797164917,
                -5.155238628387451,
                0.0047920942306518555
            ],
            "path": "./prompt_files/data/put_carboy_in_the_bin/subtask_2/seg_instance2_detect_surroundings.png"
        },
        "reagent_bottle_189": {
            "ability": [
                [
                    "heatable",
                    0
                ],
                [
                    "freezable",
                    0
                ]
            ],
            "position_in_bot": {
                "rho": 1.2777986519831164,
                "theta_deg": 124.3336612892029,
                "phi_deg": 78.87468596121239
            },
            "orientation_in_bot": [
                0.0017944523899950276,
                0.021940433299487343,
                0.08607571568419964,
                0.9960453646780871
            ],
            "position_in_world": [
                -5.548537731170654,
                -3.912888765335083,
                0.22007398307323456
            ],
            "bot_in_world": [
                -5.75587797164917,
                -5.155238628387451,
                0.0047920942306518555
            ],
            "path": "./prompt_files/data/put_carboy_in_the_bin/subtask_2/seg_instance2_detect_surroundings.png"
        },
        "bottom_cabinet_no_top_qudfwe_0": {
            "ability": [
                [
                    "openable",
                    0
                ],
                [
                    "heatable",
                    0
                ],
                [
                    "freezable",
                    0
                ]
            ],
            "position_in_bot": {
                "rho": 1.296098025909153,
                "theta_deg": 133.5265002053048,
                "phi_deg": 69.33677181039076
            },
            "orientation_in_bot": [
                0.008227525681410065,
                0.020472777400229545,
                0.3760714845158647,
                0.9263279180402134
            ],
            "position_in_world": [
                -5.7557172775268555,
                -3.9291481971740723,
                0.4249972403049469
            ],
            "bot_in_world": [
                -5.75587797164917,
                -5.155238628387451,
                0.0047920942306518555
            ],
            "path": "./prompt_files/data/put_carboy_in_the_bin/subtask_2/seg_instance2_detect_surroundings.png"
        },
        "scene_graph": [
            [
                "reagent_bottle_189",
                "inside",
                "bottom_cabinet_no_top_qudfwe_0"
            ]
        ],
        "inventory": []
    },
    "3_detect_surroundings": {
        "recycling_bin_188": {
            "ability": [
                [
                    "openable",
                    0
                ],
                [
                    "heatable",
                    0
                ],
                [
                    "freezable",
                    0
                ]
            ],
            "position_in_bot": {
                "rho": 2.41759060995763,
                "theta_deg": 90.06364566127347,
                "phi_deg": 84.32263375970346
            },
            "orientation_in_bot": [
                0.004613401342793831,
                0.023148828927239552,
                0.17622606664497878,
                0.984066675425089
            ],
            "position_in_world": [
                -4.088426113128662,
                -3.421128511428833,
                0.2439800351858139
            ],
            "bot_in_world": [
                -5.75587797164917,
                -5.155238628387451,
                0.0047920942306518555
            ],
            "path": "./prompt_files/data/put_carboy_in_the_bin/subtask_2/seg_instance3_detect_surroundings.png"
        },
        "reagent_bottle_189": {
            "ability": [
                [
                    "heatable",
                    0
                ],
                [
                    "freezable",
                    0
                ]
            ],
            "position_in_bot": {
                "rho": 1.2777986519831164,
                "theta_deg": 124.3336612892029,
                "phi_deg": 78.87468596121239
            },
            "orientation_in_bot": [
                0.0017944523899950276,
                0.021940433299487343,
                0.08607571568419964,
                0.9960453646780871
            ],
            "position_in_world": [
                -5.548537731170654,
                -3.912888765335083,
                0.22007398307323456
            ],
            "bot_in_world": [
                -5.75587797164917,
                -5.155238628387451,
                0.0047920942306518555
            ],
            "path": "./prompt_files/data/put_carboy_in_the_bin/subtask_2/seg_instance3_detect_surroundings.png"
        },
        "bottom_cabinet_no_top_qudfwe_0": {
            "ability": [
                [
                    "openable",
                    0
                ],
                [
                    "heatable",
                    0
                ],
                [
                    "freezable",
                    0
                ]
            ],
            "position_in_bot": {
                "rho": 1.296098025909153,
                "theta_deg": 133.5265002053048,
                "phi_deg": 69.33677181039076
            },
            "orientation_in_bot": [
                0.008227525681410065,
                0.020472777400229545,
                0.3760714845158647,
                0.9263279180402134
            ],
            "position_in_world": [
                -5.7557172775268555,
                -3.9291481971740723,
                0.4249972403049469
            ],
            "bot_in_world": [
                -5.75587797164917,
                -5.155238628387451,
                0.0047920942306518555
            ],
            "path": "./prompt_files/data/put_carboy_in_the_bin/subtask_2/seg_instance3_detect_surroundings.png"
        },
        "scene_graph": [
            [
                "reagent_bottle_189",
                "inside",
                "bottom_cabinet_no_top_qudfwe_0"
            ]
        ],
        "inventory": []
    },
    "4_detect_surroundings": {
        "recycling_bin_188": {
            "ability": [
                [
                    "openable",
                    0
                ],
                [
                    "heatable",
                    0
                ],
                [
                    "freezable",
                    0
                ]
            ],
            "position_in_bot": {
                "rho": 2.41759060995763,
                "theta_deg": 90.06364566127347,
                "phi_deg": 84.32263375970346
            },
            "orientation_in_bot": [
                0.004613401342793831,
                0.023148828927239552,
                0.17622606664497878,
                0.984066675425089
            ],
            "position_in_world": [
                -4.088426113128662,
                -3.421128511428833,
                0.2439800351858139
            ],
            "bot_in_world": [
                -5.75587797164917,
                -5.155238628387451,
                0.0047920942306518555
            ],
            "path": "./prompt_files/data/put_carboy_in_the_bin/subtask_2/seg_instance4_detect_surroundings.png"
        },
        "reagent_bottle_189": {
            "ability": [
                [
                    "heatable",
                    0
                ],
                [
                    "freezable",
                    0
                ]
            ],
            "position_in_bot": {
                "rho": 1.2777986519831164,
                "theta_deg": 124.3336612892029,
                "phi_deg": 78.87468596121239
            },
            "orientation_in_bot": [
                0.0017944523899950276,
                0.021940433299487343,
                0.08607571568419964,
                0.9960453646780871
            ],
            "position_in_world": [
                -5.548537731170654,
                -3.912888765335083,
                0.22007398307323456
            ],
            "bot_in_world": [
                -5.75587797164917,
                -5.155238628387451,
                0.0047920942306518555
            ],
            "path": "./prompt_files/data/put_carboy_in_the_bin/subtask_2/seg_instance4_detect_surroundings.png"
        },
        "bottom_cabinet_no_top_qudfwe_0": {
            "ability": [
                [
                    "openable",
                    0
                ],
                [
                    "heatable",
                    0
                ],
                [
                    "freezable",
                    0
                ]
            ],
            "position_in_bot": {
                "rho": 1.296098025909153,
                "theta_deg": 133.5265002053048,
                "phi_deg": 69.33677181039076
            },
            "orientation_in_bot": [
                0.008227525681410065,
                0.020472777400229545,
                0.3760714845158647,
                0.9263279180402134
            ],
            "position_in_world": [
                -5.7557172775268555,
                -3.9291481971740723,
                0.4249972403049469
            ],
            "bot_in_world": [
                -5.75587797164917,
                -5.155238628387451,
                0.0047920942306518555
            ],
            "path": "./prompt_files/data/put_carboy_in_the_bin/subtask_2/seg_instance4_detect_surroundings.png"
        },
        "scene_graph": [
            [
                "reagent_bottle_189",
                "inside",
                "bottom_cabinet_no_top_qudfwe_0"
            ]
        ],
        "inventory": []
    },
    "5_detect_surroundings": {
        "recycling_bin_188": {
            "ability": [
                [
                    "openable",
                    0
                ],
                [
                    "heatable",
                    0
                ],
                [
                    "freezable",
                    0
                ]
            ],
            "position_in_bot": {
                "rho": 2.41759060995763,
                "theta_deg": 90.06364566127347,
                "phi_deg": 84.32263375970346
            },
            "orientation_in_bot": [
                0.004613401342793831,
                0.023148828927239552,
                0.17622606664497878,
                0.984066675425089
            ],
            "position_in_world": [
                -4.088426113128662,
                -3.421128511428833,
                0.2439800351858139
            ],
            "bot_in_world": [
                -5.75587797164917,
                -5.155238628387451,
                0.0047920942306518555
            ],
            "path": "./prompt_files/data/put_carboy_in_the_bin/subtask_2/seg_instance5_detect_surroundings.png"
        },
        "reagent_bottle_189": {
            "ability": [
                [
                    "heatable",
                    0
                ],
                [
                    "freezable",
                    0
                ]
            ],
            "position_in_bot": {
                "rho": 1.2777986519831164,
                "theta_deg": 124.3336612892029,
                "phi_deg": 78.87468596121239
            },
            "orientation_in_bot": [
                0.0017944523899950276,
                0.021940433299487343,
                0.08607571568419964,
                0.9960453646780871
            ],
            "position_in_world": [
                -5.548537731170654,
                -3.912888765335083,
                0.22007398307323456
            ],
            "bot_in_world": [
                -5.75587797164917,
                -5.155238628387451,
                0.0047920942306518555
            ],
            "path": "./prompt_files/data/put_carboy_in_the_bin/subtask_2/seg_instance5_detect_surroundings.png"
        },
        "bottom_cabinet_no_top_qudfwe_0": {
            "ability": [
                [
                    "openable",
                    0
                ],
                [
                    "heatable",
                    0
                ],
                [
                    "freezable",
                    0
                ]
            ],
            "position_in_bot": {
                "rho": 1.296098025909153,
                "theta_deg": 133.5265002053048,
                "phi_deg": 69.33677181039076
            },
            "orientation_in_bot": [
                0.008227525681410065,
                0.020472777400229545,
                0.3760714845158647,
                0.9263279180402134
            ],
            "position_in_world": [
                -5.7557172775268555,
                -3.9291481971740723,
                0.4249972403049469
            ],
            "bot_in_world": [
                -5.75587797164917,
                -5.155238628387451,
                0.0047920942306518555
            ],
            "path": "./prompt_files/data/put_carboy_in_the_bin/subtask_2/seg_instance5_detect_surroundings.png"
        },
        "scene_graph": [
            [
                "reagent_bottle_189",
                "inside",
                "bottom_cabinet_no_top_qudfwe_0"
            ]
        ],
        "inventory": []
    },
    "6_detect_surroundings": {
        "recycling_bin_188": {
            "ability": [
                [
                    "openable",
                    0
                ],
                [
                    "heatable",
                    0
                ],
                [
                    "freezable",
                    0
                ]
            ],
            "position_in_bot": {
                "rho": 2.41759060995763,
                "theta_deg": 90.06364566127347,
                "phi_deg": 84.32263375970346
            },
            "orientation_in_bot": [
                0.004613401342793831,
                0.023148828927239552,
                0.17622606664497878,
                0.984066675425089
            ],
            "position_in_world": [
                -4.088426113128662,
                -3.421128511428833,
                0.2439800351858139
            ],
            "bot_in_world": [
                -5.75587797164917,
                -5.155238628387451,
                0.0047920942306518555
            ],
            "path": "./prompt_files/data/put_carboy_in_the_bin/subtask_2/seg_instance6_detect_surroundings.png"
        },
        "reagent_bottle_189": {
            "ability": [
                [
                    "heatable",
                    0
                ],
                [
                    "freezable",
                    0
                ]
            ],
            "position_in_bot": {
                "rho": 1.2777986519831164,
                "theta_deg": 124.3336612892029,
                "phi_deg": 78.87468596121239
            },
            "orientation_in_bot": [
                0.0017944523899950276,
                0.021940433299487343,
                0.08607571568419964,
                0.9960453646780871
            ],
            "position_in_world": [
                -5.548537731170654,
                -3.912888765335083,
                0.22007398307323456
            ],
            "bot_in_world": [
                -5.75587797164917,
                -5.155238628387451,
                0.0047920942306518555
            ],
            "path": "./prompt_files/data/put_carboy_in_the_bin/subtask_2/seg_instance6_detect_surroundings.png"
        },
        "bottom_cabinet_no_top_qudfwe_0": {
            "ability": [
                [
                    "openable",
                    0
                ],
                [
                    "heatable",
                    0
                ],
                [
                    "freezable",
                    0
                ]
            ],
            "position_in_bot": {
                "rho": 1.296098025909153,
                "theta_deg": 133.5265002053048,
                "phi_deg": 69.33677181039076
            },
            "orientation_in_bot": [
                0.008227525681410065,
                0.020472777400229545,
                0.3760714845158647,
                0.9263279180402134
            ],
            "position_in_world": [
                -5.7557172775268555,
                -3.9291481971740723,
                0.4249972403049469
            ],
            "bot_in_world": [
                -5.75587797164917,
                -5.155238628387451,
                0.0047920942306518555
            ],
            "path": "./prompt_files/data/put_carboy_in_the_bin/subtask_2/seg_instance6_detect_surroundings.png"
        },
        "scene_graph": [
            [
                "reagent_bottle_189",
                "inside",
                "bottom_cabinet_no_top_qudfwe_0"
            ]
        ],
        "inventory": []
    },
    "7_detect_surroundings": {
        "recycling_bin_188": {
            "ability": [
                [
                    "openable",
                    0
                ],
                [
                    "heatable",
                    0
                ],
                [
                    "freezable",
                    0
                ]
            ],
            "position_in_bot": {
                "rho": 2.41759060995763,
                "theta_deg": 90.06364566127347,
                "phi_deg": 84.32263375970346
            },
            "orientation_in_bot": [
                0.004613401342793831,
                0.023148828927239552,
                0.17622606664497878,
                0.984066675425089
            ],
            "position_in_world": [
                -4.088426113128662,
                -3.421128511428833,
                0.2439800351858139
            ],
            "bot_in_world": [
                -5.75587797164917,
                -5.155238628387451,
                0.0047920942306518555
            ],
            "path": "./prompt_files/data/put_carboy_in_the_bin/subtask_2/seg_instance7_detect_surroundings.png"
        },
        "reagent_bottle_189": {
            "ability": [
                [
                    "heatable",
                    0
                ],
                [
                    "freezable",
                    0
                ]
            ],
            "position_in_bot": {
                "rho": 1.2777986519831164,
                "theta_deg": 124.3336612892029,
                "phi_deg": 78.87468596121239
            },
            "orientation_in_bot": [
                0.0017944523899950276,
                0.021940433299487343,
                0.08607571568419964,
                0.9960453646780871
            ],
            "position_in_world": [
                -5.548537731170654,
                -3.912888765335083,
                0.22007398307323456
            ],
            "bot_in_world": [
                -5.75587797164917,
                -5.155238628387451,
                0.0047920942306518555
            ],
            "path": "./prompt_files/data/put_carboy_in_the_bin/subtask_2/seg_instance7_detect_surroundings.png"
        },
        "bottom_cabinet_no_top_qudfwe_0": {
            "ability": [
                [
                    "openable",
                    0
                ],
                [
                    "heatable",
                    0
                ],
                [
                    "freezable",
                    0
                ]
            ],
            "position_in_bot": {
                "rho": 1.296098025909153,
                "theta_deg": 133.5265002053048,
                "phi_deg": 69.33677181039076
            },
            "orientation_in_bot": [
                0.008227525681410065,
                0.020472777400229545,
                0.3760714845158647,
                0.9263279180402134
            ],
            "position_in_world": [
                -5.7557172775268555,
                -3.9291481971740723,
                0.4249972403049469
            ],
            "bot_in_world": [
                -5.75587797164917,
                -5.155238628387451,
                0.0047920942306518555
            ],
            "path": "./prompt_files/data/put_carboy_in_the_bin/subtask_2/seg_instance7_detect_surroundings.png"
        },
        "scene_graph": [
            [
                "reagent_bottle_189",
                "inside",
                "bottom_cabinet_no_top_qudfwe_0"
            ]
        ],
        "inventory": []
    },
    "8_BEV_surroundings": {
        "recycling_bin_188": {
            "ability": [
                [
                    "openable",
                    0
                ],
                [
                    "heatable",
                    0
                ],
                [
                    "freezable",
                    0
                ]
            ],
            "position_in_bot": {
                "rho": 2.417591319868464,
                "theta_deg": 90.06383855135626,
                "phi_deg": 84.32257965133388
            },
            "orientation_in_bot": [
                0.004615399627273819,
                0.023157010669753522,
                0.17622879037872105,
                0.984065985787932
            ],
            "position_in_world": [
                -4.088426113128662,
                -3.421128511428833,
                0.2439800351858139
            ],
            "bot_in_world": [
                -5.7558794021606445,
                -5.155238151550293,
                0.004792571067810059
            ],
            "path": "./prompt_files/data/put_carboy_in_the_bin/subtask_2/seg_instance8_BEV_surroundings.png"
        },
        "reagent_bottle_189": {
            "ability": [
                [
                    "heatable",
                    0
                ],
                [
                    "freezable",
                    0
                ]
            ],
            "position_in_bot": {
                "rho": 1.2777984097288153,
                "theta_deg": 124.333764499501,
                "phi_deg": 78.87410942708323
            },
            "orientation_in_bot": [
                0.00179570324281567,
                0.02194876113001663,
                0.08607849329993512,
                0.9960449389088498
            ],
            "position_in_world": [
                -5.548537731170654,
                -3.912888765335083,
                0.22007398307323456
            ],
            "bot_in_world": [
                -5.7558794021606445,
                -5.155238151550293,
                0.004792571067810059
            ],
            "path": "./prompt_files/data/put_carboy_in_the_bin/subtask_2/seg_instance8_BEV_surroundings.png"
        },
        "bottom_cabinet_no_top_qudfwe_0": {
            "ability": [
                [
                    "openable",
                    0
                ],
                [
                    "heatable",
                    0
                ],
                [
                    "freezable",
                    0
                ]
            ],
            "position_in_bot": {
                "rho": 1.2960974794237223,
                "theta_deg": 133.52650638923808,
                "phi_deg": 69.33607616700718
            },
            "orientation_in_bot": [
                0.008231177396461349,
                0.020480365820358695,
                0.37607402083530583,
                0.9263266881545075
            ],
            "position_in_world": [
                -5.7557172775268555,
                -3.9291481971740723,
                0.4249972403049469
            ],
            "bot_in_world": [
                -5.7558794021606445,
                -5.155238151550293,
                0.004792571067810059
            ],
            "path": "./prompt_files/data/put_carboy_in_the_bin/subtask_2/seg_instance8_BEV_surroundings.png"
        },
        "scene_graph": [
            [
                "reagent_bottle_189",
                "inside",
                "bottom_cabinet_no_top_qudfwe_0"
            ]
        ],
        "inventory": []
    },
    "9_BEV_surroundings": {
        "recycling_bin_188": {
            "ability": [
                [
                    "openable",
                    0
                ],
                [
                    "heatable",
                    0
                ],
                [
                    "freezable",
                    0
                ]
            ],
            "position_in_bot": {
                "rho": 2.417591319868464,
                "theta_deg": 90.06383855135626,
                "phi_deg": 84.32257965133388
            },
            "orientation_in_bot": [
                0.004615399627273819,
                0.023157010669753522,
                0.17622879037872105,
                0.984065985787932
            ],
            "position_in_world": [
                -4.088426113128662,
                -3.421128511428833,
                0.2439800351858139
            ],
            "bot_in_world": [
                -5.7558794021606445,
                -5.155238151550293,
                0.004792571067810059
            ],
            "path": "./prompt_files/data/put_carboy_in_the_bin/subtask_2/seg_instance9_BEV_surroundings.png"
        },
        "reagent_bottle_189": {
            "ability": [
                [
                    "heatable",
                    0
                ],
                [
                    "freezable",
                    0
                ]
            ],
            "position_in_bot": {
                "rho": 1.2777984097288153,
                "theta_deg": 124.333764499501,
                "phi_deg": 78.87410942708323
            },
            "orientation_in_bot": [
                0.00179570324281567,
                0.02194876113001663,
                0.08607849329993512,
                0.9960449389088498
            ],
            "position_in_world": [
                -5.548537731170654,
                -3.912888765335083,
                0.22007398307323456
            ],
            "bot_in_world": [
                -5.7558794021606445,
                -5.155238151550293,
                0.004792571067810059
            ],
            "path": "./prompt_files/data/put_carboy_in_the_bin/subtask_2/seg_instance9_BEV_surroundings.png"
        },
        "bottom_cabinet_no_top_qudfwe_0": {
            "ability": [
                [
                    "openable",
                    0
                ],
                [
                    "heatable",
                    0
                ],
                [
                    "freezable",
                    0
                ]
            ],
            "position_in_bot": {
                "rho": 1.2960974794237223,
                "theta_deg": 133.52650638923808,
                "phi_deg": 69.33607616700718
            },
            "orientation_in_bot": [
                0.008231177396461349,
                0.020480365820358695,
                0.37607402083530583,
                0.9263266881545075
            ],
            "position_in_world": [
                -5.7557172775268555,
                -3.9291481971740723,
                0.4249972403049469
            ],
            "bot_in_world": [
                -5.7558794021606445,
                -5.155238151550293,
                0.004792571067810059
            ],
            "path": "./prompt_files/data/put_carboy_in_the_bin/subtask_2/seg_instance9_BEV_surroundings.png"
        },
        "scene_graph": [
            [
                "reagent_bottle_189",
                "inside",
                "bottom_cabinet_no_top_qudfwe_0"
            ]
        ],
        "inventory": []
    }
}